sanskrit_scraper/__init__.py
sanskrit_scraper/scraper.py
sanskrit_dictionary_scraper-1.0.4.dist-info/LICENSE
sanskrit_dictionary_scraper-1.0.4.dist-info/METADATA
sanskrit_dictionary_scraper-1.0.4.dist-info/WHEEL
sanskrit_dictionary_scraper-1.0.4.dist-info/entry_points.txt
sanskrit_dictionary_scraper-1.0.4.dist-info/top_level.txt
sanskrit_dictionary_scraper-1.0.4.dist-info/RECORD
