Metadata-Version: 2.1
Name: sanskrit-dictionary-scraper
Version: 1.0.4
Summary: A package to scrape Sanskrit dictionary data
Home-page: https://github.com/jagruti0403/sanskrit-dictionary-scraper
Author: Jagruti Airao
Author-email: jagrutiairao04@gmail.com
License: UNKNOWN
Platform: UNKNOWN
Classifier: Programming Language :: Python :: 3
Classifier: License :: OSI Approved :: MIT License
Classifier: Operating System :: OS Independent
Requires-Python: >=3.6
License-File: LICENSE
Requires-Dist: beautifulsoup4
Requires-Dist: selenium
Requires-Dist: webdriver-manager
